pawel_forecasting.py
pawel_forecasting-0.0.1.1.dist-info/LICENSE
pawel_forecasting-0.0.1.1.dist-info/WHEEL
pawel_forecasting-0.0.1.1.dist-info/METADATA
pawel_forecasting-0.0.1.1.dist-info/RECORD
