Metadata-Version: 2.1
Name: pawel_forecasting
Version: 0.0.1.1
Summary: docstring
Classifier: License :: OSI Approved :: MIT License
Requires-Dist: pandas==1.5.0
